markit_processing/__init__.py
markit_processing/client/__init__.py
markit_processing/client/multical.py
markit_processing/client/realsense.py
markit_processing/cmd/__init__.py
markit_processing/cmd/create_experiment_template.py
markit_processing/cmd/launch_experiment.py
markit_processing/cmd/model.py
markit_processing/cmd/patch_experiment_target.py
markit_processing/datamodels/DataModel.py
markit_processing/datamodels/__init__.py
markit_processing/detector/OpenCVDetector.py
markit_processing/detector/__init__.py
markit_processing/detector/fiducial.py
markit_processing/detector/functional.py
markit_processing/ekf/__init__.py
markit_processing/ekf/attitude.py
markit_processing/ekf/filter.py
markit_processing/utils/__init__.py
markit_processing/utils/algorithm.py
markit_processing-0.0.1.dist-info/METADATA
markit_processing-0.0.1.dist-info/WHEEL
markit_processing-0.0.1.dist-info/top_level.txt
markit_processing-0.0.1.dist-info/RECORD
